setup.py
aconfig/__init__.py
aconfig/config.py
aconfig.egg-info/PKG-INFO
aconfig.egg-info/SOURCES.txt
aconfig.egg-info/dependency_links.txt
aconfig.egg-info/not-zip-safe
aconfig.egg-info/requires.txt
aconfig.egg-info/top_level.txt