Metadata-Version: 1.2
Name: aconfig
Version: 1.0.0
Summary: Config Files Manager for JSON and YAML files
Home-page: http://github.com/aldarien/aconfig
Author: Aldarien
Author-email: aldarien85@gmail.com
License: MIT
Platform: UNKNOWN
Requires-Python: ~=3.0
